pybn254-1.0.5.data/purelib/pybn254/__init__.py
pybn254-1.0.5.data/purelib/pybn254/libff.dylib
pybn254-1.0.5.data/purelib/pybn254/libff.so
pybn254-1.0.5.data/purelib/pybn254/ops.py
pybn254-1.0.5.dist-info/METADATA
pybn254-1.0.5.dist-info/WHEEL
pybn254-1.0.5.dist-info/top_level.txt
pybn254-1.0.5.dist-info/RECORD
