Metadata-Version: 2.1
Name: pybn254
Version: 1.0.5
Summary: Accelerated operations for BN254
Home-page: UNKNOWN
License: UNKNOWN
Platform: UNKNOWN
Requires-Dist: py-ecc
